{
  "schemaVersion": 1,
  "generatedAt": "2026-05-19T03:50:02.271Z",
  "note": "Generated by npm run performance:baseline. Budgets use current measurements plus per-category headroom.",
  "budgets": {
    "web": {
      "initial": {
        "files": 8,
        "baselineBytes": 5628498,
        "baselineGzipBytes": 1448932,
        "maxBytes": 6191348,
        "maxGzipBytes": 1593826
      },
      "runtime": {
        "files": 10,
        "baselineBytes": 26335725,
        "baselineGzipBytes": 9315414,
        "maxBytes": 26335725,
        "maxGzipBytes": 9315414
      },
      "worker": {
        "files": 8,
        "baselineBytes": 9379745,
        "baselineGzipBytes": 2126883,
        "maxBytes": 10317720,
        "maxGzipBytes": 2339572
      },
      "utility": {
        "files": 10,
        "baselineBytes": 2058382,
        "baselineGzipBytes": 543652,
        "maxBytes": 2367140,
        "maxGzipBytes": 625200
      },
      "lazy": {
        "files": 6,
        "baselineBytes": 1679896,
        "baselineGzipBytes": 466125,
        "maxBytes": 1931881,
        "maxGzipBytes": 536044
      },
      "other": {
        "files": 7,
        "baselineBytes": 219110,
        "baselineGzipBytes": 145909,
        "maxBytes": 241022,
        "maxGzipBytes": 160500
      }
    },
    "renderer": {
      "initial": {
        "files": 8,
        "baselineBytes": 5916666,
        "baselineGzipBytes": 1511089,
        "maxBytes": 6508333,
        "maxGzipBytes": 1662198
      },
      "runtime": {
        "files": 10,
        "baselineBytes": 26335725,
        "baselineGzipBytes": 9315414,
        "maxBytes": 26335725,
        "maxGzipBytes": 9315414
      },
      "worker": {
        "files": 8,
        "baselineBytes": 9379749,
        "baselineGzipBytes": 2126890,
        "maxBytes": 10317724,
        "maxGzipBytes": 2339579
      },
      "utility": {
        "files": 10,
        "baselineBytes": 2058382,
        "baselineGzipBytes": 543649,
        "maxBytes": 2367140,
        "maxGzipBytes": 625197
      },
      "lazy": {
        "files": 8,
        "baselineBytes": 1974093,
        "baselineGzipBytes": 549254,
        "maxBytes": 2270207,
        "maxGzipBytes": 631643
      },
      "other": {
        "files": 7,
        "baselineBytes": 220110,
        "baselineGzipBytes": 146209,
        "maxBytes": 242122,
        "maxGzipBytes": 160830
      }
    }
  }
}
